invoice_synchronizer/__init__.py
invoice_synchronizer/application/__init__.py
invoice_synchronizer/application/use_cases/updater.py
invoice_synchronizer/application/use_cases/utils.py
invoice_synchronizer/domain/__init__.py
invoice_synchronizer/domain/errors/__init__.py
invoice_synchronizer/domain/errors/errors.py
invoice_synchronizer/domain/models/__init__.py
invoice_synchronizer/domain/models/invoices.py
invoice_synchronizer/domain/models/products.py
invoice_synchronizer/domain/models/taxes.py
invoice_synchronizer/domain/models/user.py
invoice_synchronizer/domain/models/utils.py
invoice_synchronizer/domain/repositories/platform_connector.py
invoice_synchronizer/infrastructure/__init__.py
invoice_synchronizer/infrastructure/config.py
invoice_synchronizer/infrastructure/repositories/pirpos/pirpos.py
invoice_synchronizer/infrastructure/repositories/pirpos/utils.py
invoice_synchronizer/infrastructure/repositories/rate_limiter/rate_limiter.py
invoice_synchronizer/infrastructure/repositories/siigo/siigo.py
invoice_synchronizer/infrastructure/repositories/siigo/utils.py
invoice_synchronizer/infrastructure/repositories/utils.py
invoice_synchronizer/presentation/__init__.py
invoice_synchronizer/presentation/lib/synchronizer.py
invoice_synchronizer-3.0.0.dist-info/LICENSE
invoice_synchronizer-3.0.0.dist-info/METADATA
invoice_synchronizer-3.0.0.dist-info/WHEEL
invoice_synchronizer-3.0.0.dist-info/RECORD
