Metadata-Version: 2.1
Name: invoice_synchronizer
Version: 3.0.0
Summary: Invoice synchronization library
Author: JulianEstebanHerrera
Author-email: julianesteban.herrera@mercadolibre.com.co
Requires-Python: >=3.10,<3.11
Classifier: Programming Language :: Python :: 3
Classifier: Programming Language :: Python :: 3.10
Requires-Dist: Unidecode (>=1.3.4,<2.0.0)
Requires-Dist: lxml (>=4.9.0,<5.0.0)
Requires-Dist: openpyxl (>=3.0.10,<4.0.0)
Requires-Dist: pydantic (>=2.12.5,<3.0.0)
Requires-Dist: requests (>=2.28.0,<3.0.0)
